AUTHORS
LICENSE
README.md
setup.py
customerio/__init__.py
customerio/__version__.py
customerio/api.py
customerio/client_base.py
customerio/constants.py
customerio/regions.py
customerio/track.py
customerio.egg-info/PKG-INFO
customerio.egg-info/SOURCES.txt
customerio.egg-info/dependency_links.txt
customerio.egg-info/requires.txt
customerio.egg-info/top_level.txt
tests/__init__.py
tests/server.py
tests/test_api.py
tests/test_customerio.py