Metadata-Version: 2.1
Name: customerio
Version: 2.2
Summary: Customer.io Python bindings.
Home-page: https://github.com/customerio/customerio-python
Author: Peaberry Software Inc.
Author-email: support@customerio.com
License: BSD
Classifier: Environment :: Web Environment
Classifier: Intended Audience :: Developers
Classifier: License :: OSI Approved :: BSD License
Classifier: Operating System :: OS Independent
Classifier: Programming Language :: Python
Classifier: Programming Language :: Python :: 3.6
Classifier: Programming Language :: Python :: 3.7
Classifier: Programming Language :: Python :: 3.8
Classifier: Programming Language :: Python :: 3.9
License-File: LICENSE
License-File: AUTHORS
